grasp_nms.cp36-win_amd64.pyd
grasp_nms-1.0.2.dist-info/LICENSE
grasp_nms-1.0.2.dist-info/METADATA
grasp_nms-1.0.2.dist-info/WHEEL
grasp_nms-1.0.2.dist-info/top_level.txt
grasp_nms-1.0.2.dist-info/RECORD
